{
 "attributeNames": {
  "ageband": "Age Band",
  "bracoverage": "Coverage",
  "brafabricfamily": "Fabric Family",
  "bratype": "Bra Type",
  "brieftype": "Brief Type",
  "colorfamilyapparel": "Color Family",
  "cut": "Cut",
  "denimtreatments": "Denim Treatments",
  "dresslength": "Dress Length",
  "dressshape": "Dress Shape",
  "fitbottomwearmen": "Fit",
  "fittopwearmen": "Fit",
  "jeanslength": "Length",
  "mencasualbottomwearsize": "Size",
  "mencasualtopwearcollarneck": "Neck/Collar",
  "mencasualtopwearsize": "Size",
  "mencasualwearsetsize": "Size",
  "menethinicwearbottomwearsize": "Size",
  "menethinicwearcollarneck": "Neck/Collar",
  "menethinicwearsetsize": "Size",
  "menethinicweartopwearsize": "Size",
  "menfabric": "Fabric Family",
  "menformalbottomwearsize": "Size",
  "menformalsetsuitcollarneck": "Neck/Collar",
  "menformalsetsuitsize": "Size",
  "menformaltopwearcollarneck": "Neck/Collar",
  "menformaltopwearsize": "Size",
  "meninnerwearcollarneck": "Neck/Collar",
  "meninnerwearsize": "Size",
  "menpattern": "Pattern",
  "mensleepwearsize": "Size",
  "mensleeve": "Sleeve",
  "multipack": "Multi Pack",
  "nightweartype": "Nightwear Type",
  "occasion": "Occasion",
  "padding": "Padding",
  "setitems": "Set Items",
  "skirtlength": "Skirt Length",
  "skirtshape": "Skirt Shape",
  "sleepwearcoverage": "Length",
  "trousertype": "Trouser Type",
  "tshirttype": "Tshirt Type",
  "unisexapparel": "Unisex",
  "waistrise": "Waist Rise",
  "wiring": "Wiring",
  "withblouse": "With Blouse",
  "womenbottomwearfit": "Fit",
  "womenbrapattern": "Pattern",
  "womenbriefpattern": "Pattern",
  "womenbrieftype": "Brief Type",
  "womencasualbottomwearjeanslowersize": "Size",
  "womencasualdressjumperneckcollar": "Neck/Collar",
  "womencasualdressjumpersleeve": "Sleeve",
  "womencasualskirtpattern": "Pattern",
  "womencasualtopwearneckcollar": "Neck/Collar",
  "womencasualtopwearsize": "Size",
  "womencasualtopwearsleeve": "Sleeve",
  "womencasualweardressesjumperssize": "Size",
  "womenethinicbottomwearpattern": "Pattern",
  "womenethinicsetneckcollar": "Neck/Collar",
  "womenethinictopwearneckcollar": "Neck/Collar",
  "womenethinictopwearpattern": "Pattern",
  "womenethinicwearbottomwearsize": "Size",
  "womenethinicwearsetsize": "Size",
  "womenethinicweartopwearsize": "Size",
  "womenfabric": "Fabric Family",
  "womenformalbottomwearpattern": "Pattern",
  "womenformalbottomwearsize": "Size",
  "womenformalsetdressneckcollar": "Neck/Collar",
  "womenformalsetsuitneckcollar": "Neck/Collar",
  "womenformalsetsuitpattern": "Pattern",
  "womenformaltopwearneckcollar": "Neck/Collar",
  "womenformaltopwearsize": "Size",
  "womeninnerwearbrasize": "Size",
  "womeninnerwearbriefsize": "Size",
  "womenpattern": "Pattern",
  "womensetcontents": "Set Contents",
  "womensleepwearsize": "Size",
  "womensleeve": "Sleeve",
  "womentopwearfit": "Fit",
  "packcolor": "Pack Color",
  "collectiondateapparel": "Collection Date",
  "seasonapparel": "Season",
  "lengthapparel": "Length",
  "shapeapparel": "Shape",
  "pocketapparel": "Pocket",
  "keytrendsapparel": "Key Trends",
  "colorgroupapparel": "Color Group",
  "sportstypeapparel": "Sports Type",
  "sleevestylingapparel": "Sleeve Styling",
  "bottomlengthapparel": "Bottom Length",
  "blouseclosureapparel": "Blouse Closure",
  "stitchapparel": "Stitch",
  "bottomclosureapparel": "Bottom Closure",
  "dupattapatternapparel": "Dupatta Pattern",
  "bottomtypeapparel": "Bottom Type",
  "businesstag": "Business Tag"
 },
 "lov": {
  "ageband": [
   "16 to 22",
   "13 - 14 Years",
   "35-55",
   "55+",
   "0 - 3 Months",
   "3 - 6 Months",
   "6 - 9 Months",
   "9 - 12 Months",
   "12 - 18 Months",
   "18 - 24 Months",
   "24 - 48 Months",
   "1 - 2 Years",
   "2 - 3 Years",
   "3 - 4 Years",
   "4 - 5 Years",
   "5 - 6 Years",
   "6 -7 Years",
   "7 - 8 Years",
   "8 - 9 Years",
   "9 - 10 Years",
   "10 - 11 Years",
   "11 - 12 Years",
   "12 - 13 Years",
   "22-35"
  ],
  "bracoverage": [
   "Half Coverage",
   "Full Coverage"
  ],
  "brafabricfamily": [
   "Linen",
   "Polyester",
   "Leather",
   "Ramie",
   "Viscose",
   "Wool",
   "Cotton Lycra",
   "Viscose Lycra",
   "Lace",
   "Cotton Blend",
   "Others",
   "Denim",
   "Blend",
   "Cotton",
   "Acrylic"
  ],
  "bratype": [
   "Backless",
   "Balconette",
   "Mastectomy Bra",
   "Convertible bra",
   "Bandeau bra",
   "Sports bra",
   "Front open bra",
   "Maternity/Nursing",
   "Minimizer bra",
   "Plunge bra",
   "Seamless bra"
  ],
  "brieftype": [
   "Thongs",
   "Trunks",
   "Briefs",
   "Bikini",
   "Jockstrap"
  ],
  "colorfamilyapparel": [
   "Beige",
   "Coral",
   "Blue",
   "Brown",
   "Gold",
   "Green",
   "Grey",
   "Khaki",
   "Maroon",
   "Multi",
   "Navy",
   "Orange",
   "Peach",
   "Pink",
   "Purple",
   "Red",
   "Silver",
   "Tan",
   "Turquoise",
   "White",
   "Yellow",
   "Pewter",
   "Metallic",
   "Black"
  ],
  "cut": [
   "Single Breasted",
   "Double Breasted"
  ],
  "denimtreatments": [
   "Other",
   "Acid Wash",
   "Ruffles",
   "Piping",
   "Applique",
   "Ripped",
   "Tattered",
   "Embroidered",
   "Printed",
   "Raw Denim",
   "Rinse Washed",
   "Lightly washed",
   "Heavily washed",
   "Coated",
   "Bows"
  ],
  "dresslength": [
   "Midi",
   "Other",
   "Mini",
   "Maxi",
   "Knee-length",
   "Below knee",
   "Above knee"
  ],
  "dressshape": [
   "Peplum dress",
   "Assymetric dress",
   "Chemise",
   "Princess Panel",
   "Skater dress",
   "Shirt dress",
   "One-shoulder dress",
   "Jersey dress",
   "High-low dress",
   "Empire-line dress",
   "Blouson dress",
   "A-Line dress",
   "Shift dress",
   "Tube dress",
   "Tutu",
   "Other",
   "Tunic",
   "Drop Waist",
   "Maxi dress"
  ],
  "fitbottomwearmen": [
   "Slim fit",
   "Straight fit",
   "Comfort fit",
   "Skinny fit",
   "Other",
   "Regular fit"
  ],
  "fittopwearmen": [
   "Snug fit",
   "Slim fit",
   "Regular fit",
   "Extra Slim Fit"
  ],
  "jeanslength": [
   "3/4th length",
   "Other",
   "Knee length",
   "Ankle length"
  ],
  "mencasualbottomwearsize": [
   "27",
   "24 - 48 Months",
   "29",
   "30",
   "31",
   "32",
   "33",
   "34",
   "35",
   "36",
   "37",
   "38",
   "39",
   "40",
   "42",
   "44",
   "46",
   "48",
   "50",
   "3XL",
   "L",
   "M",
   "S",
   "XL",
   "XXL",
   "Free Size",
   "19 Inches",
   "19.5 Inches",
   "20 Inches",
   "20.5 Inches",
   "21 Inches",
   "21.5 Inches",
   "22 Inches",
   "22 - 22.5 Inches",
   "22.5 - 23 Inches",
   "23.5 - 24 Inches",
   "24.5 - 25 Inches",
   "25.5 - 26 Inches",
   "26.5 - 27 Inches",
   "27.5 - 28 Inches",
   "28.5 - 29 Inches",
   "29.5 - 30 Inches",
   "48 cms",
   "49.5 cms",
   "51 cms",
   "52 cms",
   "53.5 cms",
   "54.5 cms",
   "54.5 - 56 cms",
   "56 cms",
   "57 cms",
   "58.5 cms",
   "59.5 - 61 cms",
   "62.5 - 63 cms",
   "64.5 - 66 cms",
   "0 - 3 Months",
   "3 - 6 Months",
   "6 - 9 Months",
   "9 - 12 Months",
   "12 - 18 Months",
   "18 - 24 Months",
   "28"
  ],
  "mencasualtopwearcollarneck": [
   "Crew neck",
   "V neck",
   "Peter pan collar",
   "Shawl collar",
   "Shirt collar",
   "Mandarin collar",
   "Notched lapel",
   "Peaked lapel",
   "Roll collar",
   "Other",
   "Henley",
   "Hood",
   "Mock collar",
   "Round neck",
   "Scoop neck",
   "Button Down collar",
   "Cutaway Collar"
  ],
  "mencasualtopwearsize": [
   "3XL",
   "39",
   "24 - 48 Months",
   "18 - 24 Months",
   "12 - 18 Months",
   "9 - 12 Months",
   "6 - 9 Months",
   "3 - 6 Months",
   "0 - 3 Months",
   "37",
   "35",
   "36",
   "34",
   "XL",
   "M",
   "50",
   "49",
   "48",
   "47",
   "46",
   "45",
   "44",
   "43",
   "42",
   "41",
   "40",
   "4XL",
   "5XL",
   "6XL",
   "L",
   "S",
   "XXL",
   "XXS",
   "38",
   "XS",
   "52"
  ],
  "mencasualwearsetsize": [
   "40",
   "39",
   "38",
   "XXS",
   "XXL",
   "S",
   "L",
   "6XL",
   "5XL",
   "4XL",
   "3XL",
   "34",
   "XL",
   "37",
   "35",
   "36",
   "M",
   "50",
   "49",
   "48",
   "47",
   "46",
   "45",
   "44",
   "41",
   "42",
   "43"
  ],
  "menethinicwearbottomwearsize": [
   "27",
   "28",
   "29",
   "30",
   "31",
   "32",
   "33",
   "34",
   "35",
   "36",
   "37",
   "38",
   "39",
   "40",
   "42",
   "44",
   "46",
   "48",
   "50",
   "3XL",
   "L",
   "M",
   "S",
   "XL",
   "XS",
   "XXL",
   "Free Size",
   "0 - 3 Months",
   "3 - 6 Months",
   "6 - 9 Months",
   "9 - 12 Months",
   "12 - 18 Months",
   "18 - 24 Months",
   "24 - 48 Months",
   "19 Inches",
   "19.5 Inches",
   "20 Inches",
   "20.5 Inches",
   "21 Inches",
   "21.5 Inches",
   "22 Inches",
   "22 - 22.5 Inches",
   "22.5 - 23 Inches",
   "23.5 - 24 Inches",
   "24.5 - 25 Inches",
   "25.5 - 26 Inches",
   "26.5 - 27 Inches",
   "27.5 - 28 Inches",
   "28.5 - 29 Inches",
   "29.5 - 30 Inches",
   "48 cms",
   "49.5 cms",
   "51 cms",
   "52 cms",
   "53.5 cms",
   "54.5 cms",
   "54.5 - 56 cms",
   "56 cms",
   "57 cms",
   "58.5 cms",
   "59.5 - 61 cms",
   "62.5 - 63 cms",
   "64.5 - 66 cms"
  ],
  "menethinicwearcollarneck": [
   "Mock collar",
   "Button Down collar",
   "Shawl collar",
   "Peter pan collar",
   "Crew neck",
   "V neck",
   "Round neck",
   "Mandarin collar",
   "Others",
   "Other",
   "Cutaway Collar",
   "Roll collar",
   "Peaked lapel",
   "Notched lapel",
   "Shirt collar"
  ],
  "menethinicwearsetsize": [
   "35",
   "37",
   "3XL",
   "4XL",
   "5XL",
   "6XL",
   "L",
   "S",
   "XXL",
   "XXS",
   "38",
   "36",
   "44",
   "34",
   "XL",
   "M",
   "50",
   "49",
   "48",
   "47",
   "39",
   "45",
   "43",
   "42",
   "41",
   "40",
   "46"
  ],
  "menethinicweartopwearsize": [
   "XL",
   "34",
   "36",
   "35",
   "37",
   "XS",
   "3XL",
   "4XL",
   "5XL",
   "6XL",
   "L",
   "S",
   "XXL",
   "XXS",
   "38",
   "39",
   "40",
   "41",
   "42",
   "43",
   "44",
   "45",
   "46",
   "47",
   "48",
   "49",
   "50",
   "M"
  ],
  "menfabric": [
   "Acrylic",
   "Blend",
   "Canvas",
   "Chambray",
   "Chiffon",
   "Corduroy",
   "Cotton",
   "Cotton Jersey",
   "Cotton Lycra",
   "Cotton Polyblend",
   "Crochet",
   "Denim",
   "Down",
   "Faux Fur",
   "Faux leather",
   "Fleece",
   "Leather",
   "Linen",
   "Mesh",
   "Microfibre",
   "Modal",
   "Nylon",
   "Pique",
   "Polyamide",
   "Polyster",
   "Polyurethane",
   "Ramie",
   "Rayon",
   "Satin",
   "Seersucker",
   "Silk",
   "Synthetic",
   "Taffeta",
   "Terry",
   "Terylene",
   "Tweed",
   "Twill",
   "Velvet",
   "Viscose",
   "Viscose Lycra",
   "Wool"
  ],
  "menformalbottomwearsize": [
   "34",
   "39",
   "38",
   "40",
   "27",
   "29",
   "32",
   "33",
   "42",
   "44",
   "46",
   "48",
   "50",
   "3XL",
   "L",
   "M",
   "S",
   "XL",
   "XXL",
   "Free Size",
   "28",
   "30",
   "31",
   "35",
   "37",
   "36"
  ],
  "menformalsetsuitcollarneck": [
   "Round neck",
   "Scoop neck",
   "Button Down collar",
   "Cutaway Collar",
   "V neck",
   "Henley",
   "Hood",
   "Mock collar"
  ],
  "menformalsetsuitsize": [
   "3XL",
   "37",
   "5XL",
   "6XL",
   "L",
   "S",
   "XXL",
   "XXS",
   "38",
   "39",
   "40",
   "41",
   "42",
   "43",
   "44",
   "45",
   "46",
   "47",
   "48",
   "49",
   "50",
   "M",
   "XL",
   "34",
   "36",
   "35",
   "4XL"
  ],
  "menformaltopwearcollarneck": [
   "V neck",
   "Peter pan collar",
   "Button Down collar",
   "Scoop neck",
   "Round neck",
   "Mock collar",
   "Hood",
   "Henley",
   "Other",
   "Roll collar",
   "Peaked lapel",
   "Notched lapel",
   "Mandarin collar",
   "Shirt collar",
   "Shawl collar",
   "Cutaway Collar"
  ],
  "menformaltopwearsize": [
   "M",
   "XL",
   "XXS",
   "38",
   "39",
   "40",
   "41",
   "42",
   "43",
   "44",
   "50",
   "49",
   "48",
   "47",
   "46",
   "37",
   "35",
   "36",
   "34",
   "XXL",
   "S",
   "L",
   "6XL",
   "5XL",
   "45",
   "3XL",
   "4XL",
   "14.5",
   "15",
   "15.5",
   "16",
   "16.5",
   "17",
   "17.5",
   "18",
   "18.5",
   "19",
   "19.5",
   "20"
  ],
  "meninnerwearcollarneck": [
   "Round neck",
   "V neck",
   "Other",
   "Henley",
   "Crew neck",
   "Scoop neck"
  ],
  "meninnerwearsize": [
   "S",
   "XXL",
   "XXS",
   "38",
   "37",
   "40",
   "41",
   "42",
   "43",
   "44",
   "45",
   "46",
   "47",
   "48",
   "49",
   "50",
   "M",
   "XL",
   "36",
   "35",
   "L",
   "6XL",
   "5XL",
   "4XL",
   "3XL",
   "34",
   "39",
   "28",
   "32",
   "30"
  ],
  "menpattern": [
   "Tribal",
   "Other",
   "Embroidery",
   "Floral",
   "Others",
   "Print",
   "Solid",
   "Stripes",
   "Embellished",
   "Self",
   "Graphic",
   "Logo",
   "Geometric",
   "Polka Dot",
   "Animal Print",
   "Quilted",
   "Tie - Dye",
   "Pin Stripes",
   "Ombre",
   "Plaid",
   "Tropical",
   "Distressed",
   "Paisley",
   "Aztec",
   "Chevron",
   "Gingham",
   "Metallic",
   "Houndstooth",
   "Camo",
   "Heart",
   "Jacquard",
   "Lace",
   "Brocade",
   "Abstract",
   "Patchwork",
   "Argyle",
   "Crochet",
   "Herringbone",
   "Checks"
  ],
  "mensleepwearsize": [
   "S",
   "XXL",
   "XXS",
   "38",
   "39",
   "40",
   "41",
   "42",
   "43",
   "44",
   "45",
   "46",
   "47",
   "48",
   "49",
   "50",
   "M",
   "XL",
   "34",
   "36",
   "35",
   "37",
   "3XL",
   "4XL",
   "5XL",
   "6XL",
   "L"
  ],
  "mensleeve": [
   "3/4th sleeves",
   "Full Sleeves",
   "Short sleeves",
   "Sleeveless",
   "Shoulder straps",
   "Half Sleeves",
   "Cap sleeves",
   "Puff Sleeve",
   "Elbow sleeves",
   "Magyar Sleeves"
  ],
  "multipack": [
   "No",
   "Yes"
  ],
  "nightweartype": [
   "Capris Sets",
   "Night Gown",
   "Pyjama Sets",
   "Robe",
   "Short Sets",
   "Sleep Tees",
   "Pyjamas",
   "Singlets",
   "Chamize",
   "Nighties",
   "Shorts",
   "Night Shirts",
   "Capris",
   "Baby Dolls"
  ],
  "occasion": [
   "Ethnic Wear",
   "Casual Wear",
   "Work Wear",
   "College Look",
   "Wedding Wear",
   "Party & Club Wear",
   "Evening Wear"
  ],
  "padding": [
   "Padded",
   "Non-padded"
  ],
  "setitems": [
   "Kurta/Salwaar/Churidar & Dupatta",
   "Kurta & Dupatta",
   "Dupatta & Salwaar/Churidar",
   "Kurta & Salwaar/Churidar"
  ],
  "skirtlength": [
   "Below knee",
   "Above knee",
   "Knee length",
   "Maxi",
   "Mini",
   "Other",
   "Midi"
  ],
  "skirtshape": [
   "Wrap",
   "Other",
   "A-Line dress",
   "Blouson dress",
   "Empire-line dress",
   "High-low dress",
   "Maxi dress",
   "One-shoulder dress",
   "Peplum dress",
   "Scooter",
   "Pencil",
   "Skort",
   "Lehenga",
   "Circular",
   "Tutu",
   "Assymetric dress",
   "Bodycon dress",
   "Tube dress",
   "Skater dress",
   "Shift dress",
   "Shirt dress"
  ],
  "sleepwearcoverage": [
   "Short",
   "Capri Length",
   "Full length",
   "Knee length"
  ],
  "trousertype": [
   "Chinos",
   "Salwar",
   "Churidar",
   "Elasticated",
   "Drawstring",
   "Gathered",
   "Rouched",
   "Bermudas",
   "Pyjamas",
   "Capris",
   "Trackpants",
   "Joggers",
   "Cargos",
   "Pleated",
   "Other",
   "Flat front trousers"
  ],
  "tshirttype": [
   "Other",
   "Short Kurta",
   "Long Kurta",
   "Overlap",
   "High Low",
   "Peplum",
   "Crew T-shirt",
   "A-Line",
   "Box",
   "Turtle neck",
   "V-neck",
   "Polo",
   "Henley",
   "Chemise"
  ],
  "unisexapparel": [
   "No",
   "Yes"
  ],
  "waistrise": [
   "Low rise",
   "High rise",
   "Mid rise"
  ],
  "wiring": [
   "Non-wired",
   "Under-wired"
  ],
  "withblouse": [
   "Yes",
   "No"
  ],
  "womenbottomwearfit": [
   "Bootcut",
   "Boyfriend fit",
   "Comfort fit",
   "Regular fit",
   "Super skinny fit",
   "Skinny fit",
   "Slim fit",
   "Straight fit",
   "Relaxed Fit"
  ],
  "womenbrapattern": [
   "Solid",
   "Lace",
   "Self",
   "Striped",
   "Printed"
  ],
  "womenbriefpattern": [
   "Self",
   "Striped",
   "Printed",
   "Solid",
   "Lace"
  ],
  "womenbrieftype": [
   "Bikini",
   "Hipster",
   "G-string",
   "String Bikini",
   "Thong",
   "Boy shorts"
  ],
  "womencasualbottomwearjeanslowersize": [
   "6 - 9 Months",
   "9 - 12 Months",
   "12 - 18 Months",
   "18 - 24 Months",
   "24 - 48 Months",
   "19 Inches",
   "19.5 Inches",
   "20 Inches",
   "20.5 Inches",
   "21 Inches",
   "21.5 Inches",
   "22 Inches",
   "22 - 22.5 Inches",
   "22.5 - 23 Inches",
   "23.5 - 24 Inches",
   "24.5 - 25 Inches",
   "25.5 - 26 Inches",
   "26.5 - 27 Inches",
   "27.5 - 28 Inches",
   "28.5 - 29 Inches",
   "29.5 - 30 Inches",
   "48 cms",
   "49.5 cms",
   "51 cms",
   "52 cms",
   "53.5 cms",
   "54.5 cms",
   "54.5 - 56 cms",
   "56 cms",
   "57 cms",
   "58.5 cms",
   "59.5 - 61 cms",
   "62.5 - 63 cms",
   "64.5 - 66 cms",
   "XXS",
   "XS",
   "S",
   "M",
   "L",
   "XXL",
   "3XL",
   "4XL",
   "5XL",
   "6XL",
   "Free Size",
   "22",
   "23",
   "24",
   "25",
   "26",
   "27",
   "28",
   "29",
   "30",
   "31",
   "32",
   "33",
   "34",
   "35",
   "36",
   "37",
   "38",
   "XL",
   "39",
   "40",
   "41",
   "42",
   "43",
   "44",
   "45",
   "46",
   "47",
   "48",
   "0 - 3 Months",
   "3 - 6 Months",
   "6",
   "8",
   "10",
   "12",
   "14",
   "16",
   "18",
   "20"
  ],
  "womencasualdressjumperneckcollar": [
   "One Shoulder",
   "Shawl neck",
   "Halter neck",
   "Cowl neck",
   "Boat neck",
   "Scoop neck",
   "Band Neck",
   "Round neck",
   "Peter pan collar",
   "U neck",
   "Sweet heart neck",
   "V neck",
   "Square neck",
   "Shirt collar",
   "Off Shoulder"
  ],
  "womencasualdressjumpersleeve": [
   "Sleeveless",
   "Short sleeves",
   "Off- shoulder",
   "Full Sleeves",
   "Elbow sleeves",
   "Cap sleeve",
   "3/4th sleeves",
   "Shoulder straps"
  ],
  "womencasualskirtpattern": [
   "Solid",
   "Print",
   "Others",
   "Floral",
   "Stripes",
   "Checks",
   "Self",
   "Embellished",
   "Embroidery"
  ],
  "womencasualtopwearneckcollar": [
   "Roll collar",
   "Other",
   "Boat neck",
   "Cowl neck",
   "Halter neck",
   "Off Shoulder",
   "One Shoulder",
   "Peter pan collar",
   "Round neck",
   "Scoop neck",
   "Shawl neck",
   "Shirt collar",
   "Square neck",
   "V neck",
   "Sweet heart neck",
   "U neck",
   "Band Neck",
   "Sqaure neck",
   "Turtle neck",
   "Crew neck",
   "Henley",
   "Hood",
   "Strapless",
   "Mandarin collar",
   "Mock collar",
   "Button-down collar",
   "Cut-away collar",
   "Notched lapel",
   "Peaked lapel"
  ],
  "womencasualtopwearsize": [
   "L",
   "Free Size",
   "S",
   "XL",
   "XS",
   "XXL",
   "XXS",
   "2",
   "4",
   "6",
   "8",
   "10",
   "12",
   "14",
   "16",
   "18",
   "20",
   "28",
   "30",
   "32",
   "34",
   "36",
   "38",
   "40",
   "42",
   "44",
   "46",
   "0 - 3 Months",
   "3 - 6 Months",
   "6 - 9 Months",
   "9 - 12 Months",
   "12 - 18 Months",
   "18 - 24 Months",
   "24 - 48 Months",
   "M",
   "6XL",
   "5XL",
   "4XL",
   "3XL"
  ],
  "womencasualtopwearsleeve": [
   "Full Sleeves",
   "Short sleeve",
   "Shoulder straps",
   "Sleeveless",
   "3/4th sleeve",
   "Kimono sleeve",
   "Elbow sleeves",
   "Cuff sleeve",
   "Cap sleeves",
   "Off- shoulder"
  ],
  "womencasualweardressesjumperssize": [
   "37",
   "38",
   "39",
   "40",
   "41",
   "42",
   "43",
   "44",
   "45",
   "46",
   "47",
   "48",
   "3XL",
   "4XL",
   "5XL",
   "6XL",
   "Free Size",
   "L",
   "M",
   "S",
   "XL",
   "XS",
   "XXL",
   "XXS",
   "33",
   "22",
   "23",
   "24",
   "25",
   "26",
   "27",
   "28",
   "29",
   "30",
   "31",
   "32",
   "34",
   "35",
   "36",
   "4",
   "6",
   "8",
   "10",
   "12",
   "14",
   "16",
   "18",
   "20"
  ],
  "womenethinicbottomwearpattern": [
   "Digital",
   "Embroidered",
   "Floral",
   "Geometric",
   "Ikkat",
   "Paisley",
   "Polka dots",
   "Printed",
   "Solid",
   "Stripes",
   "Aztec",
   "Bandhani",
   "Batic",
   "Block print",
   "Checks"
  ],
  "womenethinicsetneckcollar": [
   "Cowl neck",
   "Halter neck",
   "One Shoulder",
   "Band Neck",
   "U neck",
   "Sweet heart neck",
   "V neck",
   "Square neck",
   "Shirt collar",
   "Shawl neck",
   "Scoop neck",
   "Round neck",
   "Peter pan collar",
   "Off Shoulder",
   "Boat neck"
  ],
  "womenethinictopwearneckcollar": [
   "Boat neck",
   "Cowl neck",
   "Halter neck",
   "Off Shoulder",
   "One Shoulder",
   "Peter pan collar",
   "Round neck",
   "Scoop neck",
   "Shawl neck",
   "Shirt collar",
   "Square neck",
   "V neck",
   "Sweet heart neck",
   "Other",
   "Band Neck",
   "Sqaure neck",
   "Turtle neck",
   "Crew neck",
   "Henley",
   "Hood",
   "Strapless",
   "Mandarin collar",
   "Mock collar",
   "Button-down collar",
   "Cut-away collar",
   "Notched lapel",
   "U neck",
   "Roll collar",
   "Peaked lapel"
  ],
  "womenethinictopwearpattern": [
   "Checks",
   "Block print",
   "Batic",
   "Bandhani",
   "Aztec",
   "Stripes",
   "Solid",
   "Printed",
   "Polka dots",
   "Paisley",
   "Ikkat",
   "Geometric",
   "Floral",
   "Digital",
   "Embroidered"
  ],
  "womenethinicwearbottomwearsize": [
   "22",
   "23",
   "24",
   "25",
   "26",
   "27",
   "28",
   "29",
   "30",
   "31",
   "32",
   "33",
   "34",
   "35",
   "36",
   "37",
   "38",
   "39",
   "40",
   "41",
   "42",
   "43",
   "44",
   "45",
   "46",
   "47",
   "48",
   "3XL",
   "4XL",
   "5XL",
   "6XL",
   "Free Size",
   "L",
   "M",
   "S",
   "XL",
   "XS",
   "XXL",
   "XXS",
   "0 - 3 Months",
   "3 - 6 Months",
   "6 - 9 Months",
   "9 - 12 Months",
   "12 - 18 Months",
   "18 - 24 Months",
   "24 - 48 Months",
   "19 Inches",
   "19.5 Inches",
   "20 Inches",
   "20.5 Inches",
   "21 Inches",
   "21.5 Inches",
   "22 Inches",
   "22 - 22.5 Inches",
   "22.5 - 23 Inches",
   "23.5 - 24 Inches",
   "24.5 - 25 Inches",
   "25.5 - 26 Inches",
   "26.5 - 27 Inches",
   "27.5 - 28 Inches",
   "28.5 - 29 Inches",
   "29.5 - 30 Inches",
   "48 cms",
   "49.5 cms",
   "51 cms",
   "52 cms",
   "53.5 cms",
   "54.5 cms",
   "54.5 - 56 cms",
   "56 cms",
   "57 cms",
   "58.5 cms",
   "64.5 - 66 cms",
   "59.5 - 61 cms",
   "62.5 - 63 cms"
  ],
  "womenethinicwearsetsize": [
   "XS",
   "XXL",
   "S",
   "M",
   "L",
   "Free Size",
   "6XL",
   "5XL",
   "4XL",
   "3XL",
   "46",
   "44",
   "42",
   "40",
   "38",
   "36",
   "34",
   "32",
   "30",
   "28",
   "20",
   "18",
   "16",
   "14",
   "12",
   "10",
   "8",
   "6",
   "4",
   "2",
   "XXS",
   "XL"
  ],
  "womenethinicweartopwearsize": [
   "2",
   "4",
   "6",
   "8",
   "10",
   "12",
   "14",
   "16",
   "18",
   "20",
   "28",
   "30",
   "32",
   "34",
   "36",
   "38",
   "40",
   "42",
   "44",
   "46",
   "0 - 3 Months",
   "12 - 18 Months",
   "18 - 24 Months",
   "24 - 48 Months",
   "3 - 6 Months",
   "3XL",
   "4XL",
   "5XL",
   "6 - 9 Months",
   "6XL",
   "9 - 12 Months",
   "Free Size",
   "L",
   "M",
   "S",
   "XL",
   "XS",
   "XXL",
   "XXS"
  ],
  "womenfabric": [
   "Acrylic",
   "Blended",
   "Canvas",
   "Chambray",
   "Chiffon",
   "Corduroy",
   "Cotton",
   "Cotton Jersey",
   "Cotton Lycra",
   "Cotton Polyblend",
   "Cotton Silk",
   "Crochet",
   "Denim",
   "Down",
   "Elastane",
   "Faux Fur",
   "Faux leather",
   "Flax",
   "Fleece",
   "Lace",
   "Leather",
   "Linen",
   "Linen Blend",
   "Lyocell",
   "Mesh",
   "Microfibre",
   "Modal",
   "Nylon",
   "Other",
   "Pique",
   "Polyamide",
   "Polyster",
   "Polyurethane",
   "PU",
   "PVC",
   "Ramie",
   "Rayon",
   "Rayon/Viscose",
   "Satin",
   "Seersucker",
   "Self designed/Jacquard",
   "Silk",
   "Synthetic",
   "Taffeta",
   "Tencel",
   "Terry",
   "Terylene",
   "Tweed",
   "Twill",
   "Velvet",
   "Viscose",
   "Wood",
   "Wool"
  ],
  "womenformalbottomwearpattern": [
   "Embellished",
   "Stripes",
   "Solid",
   "Print",
   "Self",
   "Floral",
   "Embroidery",
   "Checks",
   "Others"
  ],
  "womenformalbottomwearsize": [
   "3XL",
   "4XL",
   "5XL",
   "6XL",
   "Free Size",
   "L",
   "M",
   "S",
   "XL",
   "XS",
   "XXL",
   "XXS",
   "22",
   "23",
   "24",
   "25",
   "26",
   "27",
   "28",
   "29",
   "30",
   "31",
   "32",
   "33",
   "34",
   "35",
   "36",
   "37",
   "38",
   "48",
   "47",
   "46",
   "45",
   "44",
   "43",
   "42",
   "41",
   "39",
   "40"
  ],
  "womenformalsetdressneckcollar": [
   "Boat neck",
   "Cowl neck",
   "Halter neck",
   "Off Shoulder",
   "One Shoulder",
   "Peter pan collar",
   "Round neck",
   "Scoop neck",
   "Shawl neck",
   "Shirt collar",
   "Square neck",
   "V neck",
   "Sweet heart neck",
   "U neck",
   "Band Neck",
   "Sqaure neck",
   "Turtle neck"
  ],
  "womenformalsetsuitneckcollar": [
   "Peter pan collar",
   "Roll collar",
   "Peaked lapel",
   "Notched lapel",
   "Shirt collar"
  ],
  "womenformalsetsuitpattern": [
   "Solid",
   "Embellished",
   "Self",
   "Print",
   "Others",
   "Floral",
   "Embroidery",
   "Checks",
   "Stripes"
  ],
  "womenformaltopwearneckcollar": [
   "Hood",
   "Off Shoulder",
   "Sweet heart neck",
   "Square neck",
   "Cowl neck",
   "Boat neck",
   "Scoop neck",
   "V neck",
   "Crew neck",
   "Spread collar",
   "Slim collar",
   "Semi-cut away",
   "Round",
   "Open collar",
   "Mock collar",
   "Double Collar",
   "Cut-away collar",
   "Button-down collar",
   "Halter neck",
   "Other",
   "Roll collar",
   "Peaked lapel",
   "Notched lapel",
   "Mandarin collar",
   "Shirt collar",
   "Shawl collar",
   "Strapless",
   "One Shoulder",
   "Peter-Pan collar",
   "Henley"
  ],
  "womenformaltopwearsize": [
   "18",
   "16",
   "14",
   "12",
   "10",
   "36",
   "46",
   "44",
   "42",
   "40",
   "38",
   "34",
   "32",
   "30",
   "28",
   "20",
   "8",
   "6",
   "4",
   "2",
   "XXS",
   "XXL",
   "XS",
   "XL",
   "S",
   "M",
   "L",
   "Free Size",
   "6XL",
   "5XL",
   "3XL",
   "4XL"
  ],
  "womeninnerwearbrasize": [
   "38G",
   "38GG",
   "38H",
   "38HH",
   "38J",
   "38JJ",
   "38K",
   "40A",
   "40B",
   "40C",
   "40D",
   "40DD",
   "40E",
   "40F",
   "40FF",
   "40G",
   "40GG",
   "40H",
   "40HH",
   "40J",
   "40JJ",
   "40K",
   "42A",
   "42B",
   "42C",
   "42D",
   "42DD",
   "42E",
   "42F",
   "42FF",
   "42G",
   "42GG",
   "42H",
   "42HH",
   "42J",
   "42JJ",
   "42K",
   "44A",
   "44B",
   "44C",
   "44D",
   "44DD",
   "44E",
   "44F",
   "44FF",
   "44G",
   "44GG",
   "44H",
   "44HH",
   "44J",
   "44JJ",
   "44K",
   "46A",
   "46B",
   "46C",
   "46D",
   "46DD",
   "48J",
   "48JJ",
   "48K",
   "50A",
   "50B",
   "50C",
   "50D",
   "50DD",
   "50E",
   "50FF",
   "50G",
   "50GG",
   "50H",
   "50HH",
   "50JJ",
   "50F",
   "50J",
   "50K",
   "L",
   "M",
   "S",
   "XL",
   "XS",
   "XXL",
   "Plus Size",
   "28A",
   "32AA",
   "30AA",
   "34A",
   "34AA",
   "34B",
   "34C",
   "34D",
   "34E",
   "34DD",
   "34F",
   "32H",
   "32HH",
   "32J",
   "32JJ",
   "32K",
   "36A",
   "36B",
   "36C",
   "36D",
   "36DD",
   "36E",
   "36F",
   "36FF",
   "36G",
   "36GG",
   "36H",
   "36HH",
   "36J",
   "36JJ",
   "36K",
   "38A",
   "38B",
   "38C",
   "38D",
   "38DD",
   "38E",
   "38F",
   "38FF",
   "26",
   "30",
   "28B",
   "28C",
   "28DD",
   "28E",
   "28F",
   "28G",
   "28H",
   "28J",
   "28K",
   "30A",
   "30B",
   "30C",
   "30D",
   "30DD",
   "30E",
   "30F",
   "30FF",
   "30G",
   "30H",
   "30HH",
   "30J",
   "30JJ",
   "30K",
   "32A",
   "32B",
   "32C",
   "32D",
   "32DD",
   "32E",
   "32F",
   "32FF",
   "32G",
   "32GG",
   "46E",
   "46F",
   "46FF",
   "46G",
   "46GG",
   "46H",
   "46HH",
   "46J",
   "46JJ",
   "46K",
   "48A",
   "48B",
   "48C",
   "48D",
   "48DD",
   "48E",
   "48F",
   "48FF",
   "48G",
   "48GG",
   "48H",
   "48HH",
   "XXXL"
  ],
  "womeninnerwearbriefsize": [
   "L",
   "M",
   "Plus Size",
   "XXL",
   "XL",
   "XS",
   "S",
   "XXXL",
   "8",
   "10",
   "12",
   "14",
   "16",
   "32B",
   "32C",
   "32D",
   "34B",
   "34C",
   "36B",
   "36C",
   "30B",
   "30C",
   "34D"
  ],
  "womenpattern": [
   "Checks",
   "Paisley",
   "Floral",
   "Print",
   "Solid",
   "Stripes",
   "Embellished",
   "Self",
   "Graphic",
   "Logo",
   "Geometric",
   "Polka Dot",
   "Animal Print",
   "Quilted",
   "Tie - Dye",
   "Pin Stripes",
   "Ombre",
   "Plaid",
   "Tropical",
   "Distressed",
   "Aztec",
   "Chevron",
   "Gingham",
   "Metallic",
   "Houndstooth",
   "Camo",
   "Heart",
   "Jacquard",
   "Lace",
   "Brocade",
   "Abstract",
   "Patchwork",
   "Argyle",
   "Crochet",
   "Herringbone",
   "Tribal",
   "Other",
   "Others",
   "Embroidery"
  ],
  "womensetcontents": [
   "Trouser Jacket",
   "Skirt Jacket"
  ],
  "womensleepwearsize": [
   "28J",
   "28K",
   "30A",
   "30B",
   "30C",
   "30D",
   "30DD",
   "30E",
   "30F",
   "30FF",
   "30H",
   "30HH",
   "30J",
   "30JJ",
   "30K",
   "32A",
   "32B",
   "32C",
   "32D",
   "32DD",
   "32E",
   "32F",
   "32FF",
   "32G",
   "32GG",
   "32H",
   "32HH",
   "50E",
   "50F",
   "50FF",
   "50G",
   "50GG",
   "50H",
   "50HH",
   "50J",
   "50JJ",
   "50K",
   "Plus Size",
   "28A",
   "32AA",
   "30AA",
   "34A",
   "34AA",
   "34B",
   "34C",
   "34D",
   "34E",
   "34DD",
   "34F",
   "26",
   "27",
   "28",
   "29",
   "30",
   "31",
   "32",
   "33",
   "34",
   "35",
   "36",
   "37",
   "38",
   "39",
   "40",
   "41",
   "42",
   "43",
   "44",
   "45",
   "46",
   "47",
   "48",
   "3XL",
   "4XL",
   "5XL",
   "6XL",
   "Free Size",
   "L",
   "M",
   "S",
   "XL",
   "XS",
   "XXL",
   "XXS",
   "28B",
   "28C",
   "28DD",
   "28E",
   "28F",
   "28G",
   "28H",
   "42B",
   "42C",
   "42D",
   "42DD",
   "42E",
   "42F",
   "42FF",
   "42G",
   "42GG",
   "42H",
   "42HH",
   "42J",
   "42JJ",
   "42K",
   "44A",
   "44B",
   "44C",
   "44D",
   "44DD",
   "44E",
   "44F",
   "44FF",
   "44G",
   "44GG",
   "44H",
   "44HH",
   "44J",
   "44JJ",
   "44K",
   "46A",
   "46B",
   "46C",
   "46D",
   "46DD",
   "46E",
   "46F",
   "46FF",
   "46G",
   "46GG",
   "46H",
   "46HH",
   "46J",
   "46JJ",
   "46K",
   "48A",
   "48B",
   "48C",
   "48D",
   "48DD",
   "48E",
   "48F",
   "48FF",
   "48G",
   "48GG",
   "48H",
   "48HH",
   "48J",
   "48JJ",
   "48K",
   "50A",
   "50B",
   "50C",
   "50D",
   "50DD",
   "30G",
   "32J",
   "32JJ",
   "32K",
   "36A",
   "36B",
   "36C",
   "36D",
   "36DD",
   "36E",
   "36F",
   "36FF",
   "36G",
   "36GG",
   "36H",
   "36HH",
   "36J",
   "36JJ",
   "36K",
   "38A",
   "38B",
   "38C",
   "38D",
   "38DD",
   "38E",
   "38F",
   "38FF",
   "38G",
   "38GG",
   "38H",
   "38HH",
   "38J",
   "38JJ",
   "38K",
   "40B",
   "40C",
   "40D",
   "40DD",
   "40E",
   "40A",
   "40F",
   "40FF",
   "40G",
   "40GG",
   "40H",
   "40HH",
   "40J",
   "40JJ",
   "40K",
   "42A"
  ],
  "womensleeve": [
   "Full Sleeves",
   "3/4th sleeve",
   "Cap sleeves",
   "Cuff sleeve",
   "Elbow sleeves",
   "Puff Sleeve",
   "Short sleeve",
   "Shoulder straps",
   "Sleeveless",
   "Off- shoulder",
   "Magyar Sleeves",
   "Kimono sleeve"
  ],
  "womentopwearfit": [
   "Extra skinny",
   "Loose fit",
   "Slim fit",
   "Relaxed Fit",
   "Skinny",
   "Regular fit"
  ],
  "packcolor": [
   "Beige",
   "black",
   "Blue",
   "Brown",
   "Coral",
   "Gold",
   "Green",
   "Grey",
   "Khaki",
   "Maroon",
   "Metallic",
   "Multi",
   "Navy",
   "Orange",
   "Peach",
   "Pewter",
   "Pink",
   "Purple",
   "Red",
   "Silver",
   "Tan",
   "Turquoise",
   "White",
   "Yellow"
  ],
  "collectiondateapparel": [
   "Aug-2018",
   "Sep-2018",
   "Oct-2018"
  ],
  "seasonapparel": [
   "SS18",
   "AW18",
   "SS19",
   "AW19",
   "AW20",
   "SS21",
   "AW21"
  ],
  "lengthapparel": [
   "Long",
   "Short",
   "Knee Length",
   "Ankle Length",
   "Calf Length",
   "Hip Length",
   "Above Knee"
  ],
  "shapeapparel": [
   "Bodycon",
   "Hourglass",
   "Wrap",
   "Flared",
   "Tiered"
  ],
  "pocketapparel": [
   "Slit Pocket",
   "No Pocket",
   "Cross Pocket"
  ],
  "keytrendsapparel": [
   "Minimal"
  ],
  "colorgroupapparel": [
   "Pastel",
   "Aqua",
   "Indigo"
  ],
  "sportstypeapparel": [
   "Football",
   "Cricket",
   "Basketball"
  ],
  "sleevestylingapparel": [
   "Bell Sleeves",
   "Puff Sleeves"
  ],
  "bottomlengthapparel": [
   "Cropped",
   "Regular"
  ],
  "blouseclosureapparel": [
   "Button",
   "Zip"
  ],
  "stitchapparel": [
   "Semi",
   "Readymade",
   "Unstitiched"
  ],
  "bottomclosureapparel": [
   "Hook",
   "Zip",
   "Elastic"
  ],
  "dupattapatternapparel": [
   "Printed",
   "Solid",
   "Striped"
  ],
  "bottomtypeapparel": [
   "Palazzo",
   "Churidar",
   "Culottes"
  ],
  "businesstag": [
   "Lux-Marketplace",
   "Lux-Indiluxe",
   "Lux-Beauty",
   "Lux-Lux",
   "Marketplace-Marketplace",
   "Marketplace-Lux",
   "Marketplace-Indiluxe",
   "Marketplace-Beauty",
   "Indiluxe-Indiluxe",
   "Indiluxe-Lux",
   "Indiluxe-Beauty",
   "Indiluxe-Marketplace",
   "Beauty-Beauty",
   "Beauty-Indiluxe",
   "Beauty-Lux",
   "Beauty-Marketplace"
  ]
 }
}